lunar_snippets/__init__.py
lunar_snippets/check.py
lunar_snippets/data.py
lunar_snippets/result.py
lunar_snippets/variables.py
lunar_snippets-0.0.11.dist-info/METADATA
lunar_snippets-0.0.11.dist-info/WHEEL
lunar_snippets-0.0.11.dist-info/licenses/LICENSE
lunar_snippets-0.0.11.dist-info/RECORD
