Metadata-Version: 2.4
Name: lunar_snippets
Version: 0.0.11
Summary: Lunar Snippets API
Project-URL: homepage, https://earthly.dev
Project-URL: repository, https://github.com/earthly/egov
License-File: LICENSE
Classifier: Development Status :: 2 - Pre-Alpha
Classifier: Intended Audience :: Developers
Classifier: License :: OSI Approved :: Mozilla Public License 2.0 (MPL 2.0)
Classifier: Operating System :: OS Independent
Classifier: Programming Language :: Python :: 3.13
Requires-Python: >=3.13
Requires-Dist: jsonpath-ng>=1.5.3
